setup.py
dm/__init__.py
dm.zope.profile.egg-info/PKG-INFO
dm.zope.profile.egg-info/SOURCES.txt
dm.zope.profile.egg-info/dependency_links.txt
dm.zope.profile.egg-info/namespace_packages.txt
dm.zope.profile.egg-info/not-zip-safe
dm.zope.profile.egg-info/requires.txt
dm.zope.profile.egg-info/top_level.txt
dm/zope/__init__.py
dm/zope/profile/LICENSE.txt
dm/zope/profile/README.txt
dm/zope/profile/VERSION.txt
dm/zope/profile/__init__.py
dm/zope/profile/browser.py
dm/zope/profile/configure.zcml
dm/zope/profile/example_config.zcml
dm/zope/profile/interfaces.py
dm/zope/profile/meta.zcml
dm/zope/profile/metaconfigure.py
dm/zope/profile/multi_input.pt
dm/zope/profile/profile.pt
dm/zope/profile/profiler.py
dm/zope/profile/tests/__init__.py
dm/zope/profile/tests/test_profiler.py
dm/zope/profile/tests/test_zcml.py