Metadata-Version: 1.1
Name: dm.zope.profile
Version: 1.0
Summary: Profiling Zope applications (for Zope >= 4)
Home-page: https://pypi.org/project/dm.zope.profile
Author: Dieter Maurer
Author-email: dieter@handshake.de
License: BSD
Keywords: profiling zope
Platform: UNKNOWN
Classifier: Development Status :: 5 - Production/Stable
Classifier: Intended Audience :: Developers
Classifier: License :: OSI Approved :: BSD License
Classifier: Framework :: Zope
Classifier: Operating System :: OS Independent
Classifier: Programming Language :: Python :: 2.7
Classifier: Programming Language :: Python :: 3
Classifier: Topic :: Utilities
